CHANGES
LICENSE
MANIFEST.in
README
README.md
requirements.txt
setup.cfg
setup.py
logging_twitter/__init__.py
logging_twitter/handler.py
python_logging_twitter.egg-info/PKG-INFO
python_logging_twitter.egg-info/SOURCES.txt
python_logging_twitter.egg-info/dependency_links.txt
python_logging_twitter.egg-info/requires.txt
python_logging_twitter.egg-info/top_level.txt
test/testsample.py