Metadata-Version: 1.1
Name: python-logging-twitter
Version: 0.3.0
Summary: Python logging handler for Twitter.
Home-page: https://github.com/mvillares/python-logging-twitter
Author: Marcos Villares
Author-email: mvillaress@gmail.com
License: GPLv2
Platform: UNKNOWN
Classifier: Development Status :: 4 - Beta
Classifier: Intended Audience :: Developers
Classifier: License :: OSI Approved :: GNU General Public License v3 (GPLv3)
Classifier: Operating System :: OS Independent
Classifier: Programming Language :: Python
Classifier: Programming Language :: Python :: 2
Classifier: Programming Language :: Python :: 3
Classifier: Topic :: Software Development :: Libraries :: Python Modules
Classifier: Topic :: System :: Logging
